qdx/__init__.py
qdx/__main__.py
qdx/api.py
qdx/calcq.py
qdx/data.py
qdx-0.10.0.dist-info/METADATA
qdx-0.10.0.dist-info/WHEEL
qdx-0.10.0.dist-info/entry_points.txt
qdx-0.10.0.dist-info/RECORD
