Metadata-Version: 2.1
Name: qdx
Version: 0.10.0
Summary: Python SDK for interacting with the QDX API
Author: Ryan Swart
Author-email: ryan@talosystems.com
Requires-Python: >=3.10,<4.0
Classifier: Programming Language :: Python :: 3
Classifier: Programming Language :: Python :: 3.10
Classifier: Programming Language :: Python :: 3.11
Requires-Dist: dataclasses-json (>=0.5.7,<0.6.0)
Requires-Dist: datargs (>=0.11.0,<0.12.0)
Requires-Dist: gql[requests] (>=3.4.0,<4.0.0)
Requires-Dist: rdkit-pypi (>=2022.9.5,<2023.0.0)
Requires-Dist: typed-argument-parser (>=1.7.2,<2.0.0)
